flask_pw/__init__.py
flask_pw/debugtoolbar.py
flask_pw/models.py
Flask_PW3-0.0.2.dist-info/AUTHORS.rst
Flask_PW3-0.0.2.dist-info/LICENSE
Flask_PW3-0.0.2.dist-info/METADATA
Flask_PW3-0.0.2.dist-info/WHEEL
Flask_PW3-0.0.2.dist-info/top_level.txt
Flask_PW3-0.0.2.dist-info/RECORD
